multi_repo_workspace/__init__.py
multi_repo_workspace/__main__.py
multi_repo_workspace/cli.py
multi_repo_workspace/config.py
multi_repo_workspace/use_case.py
multi_repo_workspace/workspace.py
multi_repo_workspace-0.0.2.dist-info/METADATA
multi_repo_workspace-0.0.2.dist-info/WHEEL
multi_repo_workspace-0.0.2.dist-info/entry_points.txt
multi_repo_workspace-0.0.2.dist-info/licenses/LICENSE
multi_repo_workspace-0.0.2.dist-info/RECORD
