Metadata-Version: 2.3
Name: multi-repo-workspace
Version: 0.0.2
Summary: Command Line Interface for managing projects in a multi-repository context by configuration.
Project-URL: Homepage, https://github.com/maximeduf/multi-repo-workspace
Project-URL: Issues, https://github.com/maximeduf/multi-repo-workspace/issues
Author-email: Maxime Dufresne <maxm.dufresne@gmail.com>
License: MIT License
License-File: LICENSE
Classifier: Development Status :: 2 - Pre-Alpha
Classifier: Intended Audience :: Developers
Classifier: License :: OSI Approved :: MIT License
Classifier: Operating System :: POSIX :: Linux
Classifier: Programming Language :: Python :: 3
Classifier: Programming Language :: Python :: 3.13
Requires-Python: >=3.11
Requires-Dist: click==8.1.7
Requires-Dist: coverage==7.6.4
Requires-Dist: packaging==24.1
Requires-Dist: pkginfo==1.10.*
Requires-Dist: prompt-toolkit==3.0.48
Requires-Dist: pygments==2.18.0
Requires-Dist: regex==2024.9.11
Provides-Extra: test
Requires-Dist: iniconfig==2.0.0; extra == 'test'
Requires-Dist: pluggy==1.5.0; extra == 'test'
Requires-Dist: pytest-cov==5.0.0; extra == 'test'
Requires-Dist: pytest==8.3.3; extra == 'test'
